cte_forest/__init__.py
cte_forest/fields.py
cte_forest/models.py
cte_forest/query.py
django_cte_forest-0.2.2.dist-info/DESCRIPTION.rst
django_cte_forest-0.2.2.dist-info/METADATA
django_cte_forest-0.2.2.dist-info/RECORD
django_cte_forest-0.2.2.dist-info/WHEEL
django_cte_forest-0.2.2.dist-info/metadata.json
django_cte_forest-0.2.2.dist-info/top_level.txt
