Metadata-Version: 2.0
Name: django-cte-forest
Version: 0.2.2
Summary: Django Adjacency-List trees using PostgreSQL Common Table Expressions (CTE).
Home-page: https://github.com/matthiask/django-cte-forest
Author: Matthias Kestenholz
Author-email: mk@feinheit.ch
License: BSD License
Platform: UNKNOWN
Classifier: Development Status :: 3 - Alpha
Classifier: Environment :: Web Environment
Classifier: Framework :: Django
Classifier: Intended Audience :: Developers
Classifier: License :: OSI Approved :: BSD License
Classifier: Operating System :: OS Independent
Classifier: Programming Language :: Python
Classifier: Topic :: Software Development :: Libraries :: Python Modules
